{"_invocation_id": "9271b740-85eb-405c-b045-bd8c28cad7b1", "linked": {"0": {"name": "source.enpal_assessment_project.postgres_public.activity_types", "type": "source"}, "1": {"name": "source.enpal_assessment_project.postgres_public.activity", "type": "source"}, "2": {"name": "source.enpal_assessment_project.postgres_public.deal_changes", "type": "source"}, "3": {"name": "source.enpal_assessment_project.postgres_public.fields", "type": "source"}, "4": {"name": "source.enpal_assessment_project.postgres_public.stages", "type": "source"}, "5": {"name": "source.enpal_assessment_project.postgres_public.users", "type": "source"}}}